LICENSE
MANIFEST.in
README.md
setup.cfg
setup.py
tap_facebook_reviews/__init__.py
tap_facebook_reviews/context.py
tap_facebook_reviews/http.py
tap_facebook_reviews/schemas.py
tap_facebook_reviews/streams.py
tap_facebook_reviews.egg-info/PKG-INFO
tap_facebook_reviews.egg-info/SOURCES.txt
tap_facebook_reviews.egg-info/dependency_links.txt
tap_facebook_reviews.egg-info/entry_points.txt
tap_facebook_reviews.egg-info/requires.txt
tap_facebook_reviews.egg-info/top_level.txt
tap_facebook_reviews/schemas/picture.json
tap_facebook_reviews/schemas/ratings.json